{
	"name": "simple-sd-audio",
	"description": "Play audio files with your Arduino in decent quality from SD card.",
	"homepage": "http://www.hackerspace-ffm.de/wiki/index.php?title=SimpleSDAudio",
	"versions": {
		"1.03": "http://www.hackerspace-ffm.de/wiki/index.php?title=Datei:SimpleSDAudio_V1.03.zip",
		"1.02": "http://www.hackerspace-ffm.de/wiki/index.php?title=Datei:SimpleSDAudio_V1.02.zip",
		"1.01": "http://www.hackerspace-ffm.de/wiki/index.php?title=Datei:SimpleSDAudio_V1.01.zip",
		"1.00": "http://www.hackerspace-ffm.de/wiki/index.php?title=Datei:SimpleSDAudio_V1.00.zip"
	}
}